<xdc.runtime.Types.RtaDecoderData>
  <targetName>ti.targets.arm.elf.M4F</targetName>
  <binaryParser>ti.targets.omf.elf.Elf32</binaryParser>
  <endian>little</endian>
  <bitsPerChar>8</bitsPerChar>
  <argSize>4</argSize>
  <eventSize>48</eventSize>
  <dataTransportClassName>undefined</dataTransportClassName>
  <controlTransportClassName>undefined</controlTransportClassName>
  <loggers-length>3</loggers-length>
  <loggers>
    <name>Load Logger</name>
    <type>ti.uia.runtime.LoggerStopMode</type>
    <metaArgs>
      <instanceId>1</instanceId>
      <priority>1</priority>
    </metaArgs>
  </loggers>
  <loggers>
    <name>Main Logger</name>
    <type>ti.uia.runtime.LoggerStopMode</type>
    <metaArgs>
      <instanceId>2</instanceId>
      <priority>1</priority>
    </metaArgs>
  </loggers>
  <loggers>
    <name>SYSBIOS System Logger</name>
    <type>ti.uia.runtime.LoggerStopMode</type>
    <metaArgs>
      <instanceId>3</instanceId>
      <priority>1</priority>
    </metaArgs>
  </loggers>
  <modMap-length>50</modMap-length>
  <modMap key="xdc.runtime.Assert">
    <id>32770</id>
    <logger>null</logger>
    <diagsMask>0000100000000000</diagsMask>
  </modMap>
  <modMap key="xdc.runtime.Core">
    <id>32771</id>
    <logger>null</logger>
    <diagsMask>0000100000000000</diagsMask>
  </modMap>
  <modMap key="xdc.runtime.Defaults">
    <id>32772</id>
    <logger>null</logger>
    <diagsMask>0000110000000000</diagsMask>
  </modMap>
  <modMap key="xdc.runtime.Diags">
    <id>32773</id>
    <logger>null</logger>
    <diagsMask>0000100000000000</diagsMask>
  </modMap>
  <modMap key="xdc.runtime.Error">
    <id>32774</id>
    <logger>null</logger>
    <diagsMask>0000110000000000</diagsMask>
  </modMap>
  <modMap key="xdc.runtime.Gate">
    <id>32775</id>
    <logger>null</logger>
    <diagsMask>0000100000000000</diagsMask>
  </modMap>
  <modMap key="xdc.runtime.Log">
    <id>32776</id>
    <logger>null</logger>
    <diagsMask>0000100000000000</diagsMask>
  </modMap>
  <modMap key="xdc.runtime.Main">
    <id>32777</id>
    <logger>Main Logger</logger>
    <diagsMask>0000130033333333</diagsMask>
  </modMap>
  <modMap key="xdc.runtime.Memory">
    <id>32778</id>
    <logger>null</logger>
    <diagsMask>0000100000000000</diagsMask>
  </modMap>
  <modMap key="xdc.runtime.Registry">
    <id>32779</id>
    <logger>Main Logger</logger>
    <diagsMask>0000110000000000</diagsMask>
  </modMap>
  <modMap key="xdc.runtime.Startup">
    <id>32780</id>
    <logger>null</logger>
    <diagsMask>0000100000000000</diagsMask>
  </modMap>
  <modMap key="xdc.runtime.System">
    <id>32781</id>
    <logger>null</logger>
    <diagsMask>0000100000000000</diagsMask>
  </modMap>
  <modMap key="xdc.runtime.SysMin">
    <id>32782</id>
    <logger>null</logger>
    <diagsMask>0000100000000000</diagsMask>
  </modMap>
  <modMap key="xdc.runtime.Text">
    <id>32783</id>
    <logger>null</logger>
    <diagsMask>0000100000000000</diagsMask>
  </modMap>
  <modMap key="xdc.runtime.Timestamp">
    <id>32784</id>
    <logger>null</logger>
    <diagsMask>0000100000000000</diagsMask>
  </modMap>
  <modMap key="xdc.runtime.TimestampNull">
    <id>32785</id>
    <logger>null</logger>
    <diagsMask>0000100000000000</diagsMask>
  </modMap>
  <modMap key="xdc.runtime.Types">
    <id>32786</id>
    <logger>null</logger>
    <diagsMask>0000100000000000</diagsMask>
  </modMap>
  <modMap key="ti.catalog.arm.cortexm4.tiva.ce.Boot">
    <id>32792</id>
    <logger>null</logger>
    <diagsMask>0000110000000000</diagsMask>
  </modMap>
  <modMap key="ti.sysbios.BIOS">
    <id>32794</id>
    <logger>null</logger>
    <diagsMask>0000110000000000</diagsMask>
  </modMap>
  <modMap key="ti.sysbios.hal.Hwi">
    <id>32796</id>
    <logger>null</logger>
    <diagsMask>0000110000000000</diagsMask>
  </modMap>
  <modMap key="ti.sysbios.hal.Timer">
    <id>32797</id>
    <logger>null</logger>
    <diagsMask>0000110000000000</diagsMask>
  </modMap>
  <modMap key="ti.sysbios.knl.Clock">
    <id>32799</id>
    <logger>null</logger>
    <diagsMask>0000110000000000</diagsMask>
  </modMap>
  <modMap key="ti.sysbios.knl.Idle">
    <id>32800</id>
    <logger>null</logger>
    <diagsMask>0000110000000000</diagsMask>
  </modMap>
  <modMap key="ti.sysbios.knl.Intrinsics">
    <id>32801</id>
    <logger>null</logger>
    <diagsMask>0000110000000000</diagsMask>
  </modMap>
  <modMap key="ti.sysbios.knl.Event">
    <id>32802</id>
    <logger>SYSBIOS System Logger</logger>
    <diagsMask>0000110033000000</diagsMask>
  </modMap>
  <modMap key="ti.sysbios.knl.Queue">
    <id>32803</id>
    <logger>null</logger>
    <diagsMask>0000110000000000</diagsMask>
  </modMap>
  <modMap key="ti.sysbios.knl.Semaphore">
    <id>32804</id>
    <logger>SYSBIOS System Logger</logger>
    <diagsMask>0000110033000000</diagsMask>
  </modMap>
  <modMap key="ti.sysbios.knl.Swi">
    <id>32805</id>
    <logger>null</logger>
    <diagsMask>0000110000000000</diagsMask>
  </modMap>
  <modMap key="ti.sysbios.knl.Task">
    <id>32806</id>
    <logger>SYSBIOS System Logger</logger>
    <diagsMask>0000110033000000</diagsMask>
  </modMap>
  <modMap key="ti.sysbios.family.arm.m3.Hwi">
    <id>32810</id>
    <logger>null</logger>
    <diagsMask>0000110000000000</diagsMask>
  </modMap>
  <modMap key="ti.sysbios.family.arm.m3.IntrinsicsSupport">
    <id>32811</id>
    <logger>null</logger>
    <diagsMask>0000110000000000</diagsMask>
  </modMap>
  <modMap key="ti.sysbios.family.arm.m3.TaskSupport">
    <id>32812</id>
    <logger>null</logger>
    <diagsMask>0000110000000000</diagsMask>
  </modMap>
  <modMap key="ti.sysbios.family.arm.lm4.TimestampProvider">
    <id>32814</id>
    <logger>null</logger>
    <diagsMask>0000100000000000</diagsMask>
  </modMap>
  <modMap key="ti.sysbios.family.arm.lm4.Timer">
    <id>32815</id>
    <logger>null</logger>
    <diagsMask>0000110000000000</diagsMask>
  </modMap>
  <modMap key="ti.sysbios.heaps.HeapMem">
    <id>32817</id>
    <logger>null</logger>
    <diagsMask>0000110000000000</diagsMask>
  </modMap>
  <modMap key="ti.uia.events.DvtTypes">
    <id>32820</id>
    <logger>null</logger>
    <diagsMask>0000110000000000</diagsMask>
  </modMap>
  <modMap key="ti.uia.events.UIABenchmark">
    <id>32821</id>
    <logger>null</logger>
    <diagsMask>0000110000000000</diagsMask>
  </modMap>
  <modMap key="ti.uia.events.UIAErr">
    <id>32822</id>
    <logger>null</logger>
    <diagsMask>0000110000000000</diagsMask>
  </modMap>
  <modMap key="ti.uia.events.UIAEvt">
    <id>32823</id>
    <logger>null</logger>
    <diagsMask>0000110000000000</diagsMask>
  </modMap>
  <modMap key="ti.uia.events.UIARoundtrip">
    <id>32824</id>
    <logger>null</logger>
    <diagsMask>0000110000000000</diagsMask>
  </modMap>
  <modMap key="ti.uia.events.UIAStatistic">
    <id>32825</id>
    <logger>null</logger>
    <diagsMask>0000110000000000</diagsMask>
  </modMap>
  <modMap key="ti.uia.events.UIASync">
    <id>32826</id>
    <logger>null</logger>
    <diagsMask>0000110000000000</diagsMask>
  </modMap>
  <modMap key="ti.uia.runtime.LogSync">
    <id>32828</id>
    <logger>null</logger>
    <diagsMask>0000110000000000</diagsMask>
  </modMap>
  <modMap key="ti.uia.runtime.LoggerStopMode">
    <id>32829</id>
    <logger>null</logger>
    <diagsMask>0000110000000000</diagsMask>
  </modMap>
  <modMap key="ti.uia.runtime.QueueDescriptor">
    <id>32830</id>
    <logger>null</logger>
    <diagsMask>0000110000000000</diagsMask>
  </modMap>
  <modMap key="ti.uia.runtime.UIAMetaData">
    <id>32831</id>
    <logger>null</logger>
    <diagsMask>0000110000000000</diagsMask>
  </modMap>
  <modMap key="ti.drivers.GPIO">
    <id>14</id>
    <logger>null</logger>
    <diagsMask>0000000000000000</diagsMask>
  </modMap>
  <modMap key="ti.sysbios.gates.GateHwi">
    <id>32833</id>
    <logger>null</logger>
    <diagsMask>0000110000000000</diagsMask>
  </modMap>
  <modMap key="ti.sysbios.gates.GateMutex">
    <id>32834</id>
    <logger>null</logger>
    <diagsMask>0000110000000000</diagsMask>
  </modMap>
  <modMap key="ti.sysbios.utils.Load">
    <id>32836</id>
    <logger>Load Logger</logger>
    <diagsMask>0000110000030000</diagsMask>
  </modMap>
  <evtMap-length>95</evtMap-length>
  <evtMap key="xdc.runtime.Log.L_construct">
    <id>4750</id>
    <msg>%3C--+construct%3A+%25p%28%27%25s%27%29</msg>
  </evtMap>
  <evtMap key="xdc.runtime.Log.L_create">
    <id>4774</id>
    <msg>%3C--+create%3A+%25p%28%27%25s%27%29</msg>
  </evtMap>
  <evtMap key="xdc.runtime.Log.L_destruct">
    <id>4795</id>
    <msg>--%3E+destruct%3A+%28%25p%29</msg>
  </evtMap>
  <evtMap key="xdc.runtime.Log.L_delete">
    <id>4814</id>
    <msg>--%3E+delete%3A+%28%25p%29</msg>
  </evtMap>
  <evtMap key="xdc.runtime.Log.L_error">
    <id>4831</id>
    <msg>ERROR%3A+%25%24F%25%24S</msg>
  </evtMap>
  <evtMap key="xdc.runtime.Log.L_warning">
    <id>4845</id>
    <msg>WARNING%3A+%25%24F%25%24S</msg>
  </evtMap>
  <evtMap key="xdc.runtime.Log.L_info">
    <id>4861</id>
    <msg>%25%24F%25%24S</msg>
  </evtMap>
  <evtMap key="xdc.runtime.Log.L_start">
    <id>4868</id>
    <msg>Start%3A+%25%24S</msg>
  </evtMap>
  <evtMap key="xdc.runtime.Log.L_stop">
    <id>4879</id>
    <msg>Stop%3A+%25%24S</msg>
  </evtMap>
  <evtMap key="xdc.runtime.Log.L_startInstance">
    <id>4889</id>
    <msg>StartInstance%3A+%25%24S</msg>
  </evtMap>
  <evtMap key="xdc.runtime.Log.L_stopInstance">
    <id>4908</id>
    <msg>StopInstance%3A+%25%24S</msg>
  </evtMap>
  <evtMap key="ti.sysbios.knl.Clock.LW_delayed">
    <id>4926</id>
    <msg>LW_delayed%3A+delay%3A+%25d</msg>
  </evtMap>
  <evtMap key="ti.sysbios.knl.Clock.LM_tick">
    <id>4948</id>
    <msg>LM_tick%3A+tick%3A+%25d</msg>
  </evtMap>
  <evtMap key="ti.sysbios.knl.Clock.LM_begin">
    <id>4966</id>
    <msg>LM_begin%3A+clk%3A+0x%25x%2C+func%3A+0x%25x</msg>
  </evtMap>
  <evtMap key="ti.sysbios.knl.Event.LM_post">
    <id>4998</id>
    <msg>LM_post%3A+event%3A+0x%25x%2C+currEvents%3A+0x%25x%2C+eventId%3A+0x%25x</msg>
  </evtMap>
  <evtMap key="ti.sysbios.knl.Event.LM_pend">
    <id>5052</id>
    <msg>LM_pend%3A+event%3A+0x%25x%2C+currEvents%3A+0x%25x%2C+andMask%3A+0x%25x%2C+orMask%3A+0x%25x%2C+timeout%3A+%25d</msg>
  </evtMap>
  <evtMap key="ti.sysbios.knl.Semaphore.LM_post">
    <id>5133</id>
    <msg>LM_post%3A+sem%3A+0x%25x%2C+count%3A+%25d</msg>
  </evtMap>
  <evtMap key="ti.sysbios.knl.Semaphore.LM_pend">
    <id>5163</id>
    <msg>LM_pend%3A+sem%3A+0x%25x%2C+count%3A+%25d%2C+timeout%3A+%25d</msg>
  </evtMap>
  <evtMap key="ti.sysbios.knl.Swi.LM_begin">
    <id>5206</id>
    <msg>LM_begin%3A+swi%3A+0x%25x%2C+func%3A+0x%25x%2C+preThread%3A+%25d</msg>
  </evtMap>
  <evtMap key="ti.sysbios.knl.Swi.LD_end">
    <id>5253</id>
    <msg>LD_end%3A+swi%3A+0x%25x</msg>
  </evtMap>
  <evtMap key="ti.sysbios.knl.Swi.LM_post">
    <id>5271</id>
    <msg>LM_post%3A+swi%3A+0x%25x%2C+func%3A+0x%25x%2C+pri%3A+%25d</msg>
  </evtMap>
  <evtMap key="ti.sysbios.knl.Task.LM_switch">
    <id>5311</id>
    <msg>LM_switch%3A+oldtsk%3A+0x%25x%2C+oldfunc%3A+0x%25x%2C+newtsk%3A+0x%25x%2C+newfunc%3A+0x%25x</msg>
  </evtMap>
  <evtMap key="ti.sysbios.knl.Task.LM_sleep">
    <id>5379</id>
    <msg>LM_sleep%3A+tsk%3A+0x%25x%2C+func%3A+0x%25x%2C+timeout%3A+%25d</msg>
  </evtMap>
  <evtMap key="ti.sysbios.knl.Task.LD_ready">
    <id>5424</id>
    <msg>LD_ready%3A+tsk%3A+0x%25x%2C+func%3A+0x%25x%2C+pri%3A+%25d</msg>
  </evtMap>
  <evtMap key="ti.sysbios.knl.Task.LD_block">
    <id>5465</id>
    <msg>LD_block%3A+tsk%3A+0x%25x%2C+func%3A+0x%25x</msg>
  </evtMap>
  <evtMap key="ti.sysbios.knl.Task.LM_yield">
    <id>5497</id>
    <msg>LM_yield%3A+tsk%3A+0x%25x%2C+func%3A+0x%25x%2C+currThread%3A+%25d</msg>
  </evtMap>
  <evtMap key="ti.sysbios.knl.Task.LM_setPri">
    <id>5545</id>
    <msg>LM_setPri%3A+tsk%3A+0x%25x%2C+func%3A+0x%25x%2C+oldPri%3A+%25d%2C+newPri+%25d</msg>
  </evtMap>
  <evtMap key="ti.sysbios.knl.Task.LD_exit">
    <id>5601</id>
    <msg>LD_exit%3A+tsk%3A+0x%25x%2C+func%3A+0x%25x</msg>
  </evtMap>
  <evtMap key="ti.sysbios.knl.Task.LM_setAffinity">
    <id>5632</id>
    <msg>LM_setAffinity%3A+tsk%3A+0x%25x%2C+func%3A+0x%25x%2C+oldCore%3A+%25d%2C+oldAffinity+%25d%2C+newAffinity+%25d</msg>
  </evtMap>
  <evtMap key="ti.sysbios.knl.Task.LM_schedule">
    <id>5715</id>
    <msg>LD_schedule%3A+coreId%3A+%25d%2C+workFlag%3A+%25d%2C+curSetLocal%3A+%25d%2C+curSetX%3A+%25d%2C+curMaskLocal%3A+%25d</msg>
  </evtMap>
  <evtMap key="ti.sysbios.knl.Task.LM_noWork">
    <id>5801</id>
    <msg>LD_noWork%3A+coreId%3A+%25d%2C+curSetLocal%3A+%25d%2C+curSetX%3A+%25d%2C+curMaskLocal%3A+%25d</msg>
  </evtMap>
  <evtMap key="ti.sysbios.family.arm.m3.Hwi.LM_begin">
    <id>5871</id>
    <msg>LM_begin%3A+hwi%3A+0x%25x%2C+func%3A+0x%25x%2C+preThread%3A+%25d%2C+intNum%3A+%25d%2C+irp%3A+0x%25x</msg>
  </evtMap>
  <evtMap key="ti.sysbios.family.arm.m3.Hwi.LD_end">
    <id>5941</id>
    <msg>LD_end%3A+hwi%3A+0x%25x</msg>
  </evtMap>
  <evtMap key="ti.uia.events.UIABenchmark.start">
    <id>5959</id>
    <msg>Start%3A+%25%24S+</msg>
  </evtMap>
  <evtMap key="ti.uia.events.UIABenchmark.stop">
    <id>5971</id>
    <msg>Stop%3A+%25%24S+</msg>
  </evtMap>
  <evtMap key="ti.uia.events.UIABenchmark.startInstance">
    <id>5982</id>
    <msg>StartInstance%3A+%25%24S+</msg>
  </evtMap>
  <evtMap key="ti.uia.events.UIABenchmark.stopInstance">
    <id>6002</id>
    <msg>StopInstance%3A+%25%24S+</msg>
  </evtMap>
  <evtMap key="ti.uia.events.UIABenchmark.startInstanceWithAdrs">
    <id>6021</id>
    <msg>StartInstanceWithAdrs%3A+%25%24S</msg>
  </evtMap>
  <evtMap key="ti.uia.events.UIABenchmark.stopInstanceWithAdrs">
    <id>6048</id>
    <msg>StopInstanceWithAdrs%3A+%25%24S</msg>
  </evtMap>
  <evtMap key="ti.uia.events.UIABenchmark.startInstanceWithStr">
    <id>6074</id>
    <msg>StartInstanceWithStr%3A+%25%24S</msg>
  </evtMap>
  <evtMap key="ti.uia.events.UIABenchmark.stopInstanceWithStr">
    <id>6100</id>
    <msg>StopInstanceWithStr%3A+%25%24S</msg>
  </evtMap>
  <evtMap key="ti.uia.events.UIAErr.error">
    <id>6125</id>
    <msg>ERROR%3A+ErrorCode%3A0x%25x</msg>
  </evtMap>
  <evtMap key="ti.uia.events.UIAErr.errorWithStr">
    <id>6147</id>
    <msg>ERROR%3A+ErrorCode%3A0x%25x.+%25%24S</msg>
  </evtMap>
  <evtMap key="ti.uia.events.UIAErr.hwError">
    <id>6174</id>
    <msg>HW+ERROR%3A+ErrorCode%3A0x%25x</msg>
  </evtMap>
  <evtMap key="ti.uia.events.UIAErr.hwErrorWithStr">
    <id>6199</id>
    <msg>HW+ERROR%3A+ErrorCode%3A0x%25x.+%25%24S</msg>
  </evtMap>
  <evtMap key="ti.uia.events.UIAErr.fatal">
    <id>6229</id>
    <msg>FATAL+ERROR%3A+ErrorCode%3A0x%25x</msg>
  </evtMap>
  <evtMap key="ti.uia.events.UIAErr.fatalWithStr">
    <id>6257</id>
    <msg>FATAL+ERROR%3A+ErrorCode%3A0x%25x.+%25%24S</msg>
  </evtMap>
  <evtMap key="ti.uia.events.UIAErr.critical">
    <id>6290</id>
    <msg>CRITICAL+ERROR%3A+ErrorCode%3A0x%25x</msg>
  </evtMap>
  <evtMap key="ti.uia.events.UIAErr.criticalWithStr">
    <id>6321</id>
    <msg>CRITICAL+ERROR%3A+ErrorCode%3A0x%25x.+%25%24S</msg>
  </evtMap>
  <evtMap key="ti.uia.events.UIAErr.exception">
    <id>6357</id>
    <msg>ERROR%3A+Exception+at+%25%24F.</msg>
  </evtMap>
  <evtMap key="ti.uia.events.UIAErr.uncaughtException">
    <id>6382</id>
    <msg>ERROR%3A+Uncaught+Exception+at+%25%24F.</msg>
  </evtMap>
  <evtMap key="ti.uia.events.UIAErr.nullPointerException">
    <id>6416</id>
    <msg>ERROR%3A+Null+Pointer+Exception+at+%25%24F.</msg>
  </evtMap>
  <evtMap key="ti.uia.events.UIAErr.unexpectedInterrupt">
    <id>6454</id>
    <msg>ERROR%3A+Unexpected+Interrupt+at+%25%24F.</msg>
  </evtMap>
  <evtMap key="ti.uia.events.UIAErr.memoryAccessFault">
    <id>6490</id>
    <msg>ERROR%3A+Memory+Access+Fault+at+%25%24F.+%5BADRS%5D0x%25x</msg>
  </evtMap>
  <evtMap key="ti.uia.events.UIAErr.securityException">
    <id>6536</id>
    <msg>ERROR%3A+Security+Exception+at+%25%24F.</msg>
  </evtMap>
  <evtMap key="ti.uia.events.UIAErr.divisionByZero">
    <id>6570</id>
    <msg>ERROR%3A+Division+by+zero+at+%25%24F.</msg>
  </evtMap>
  <evtMap key="ti.uia.events.UIAErr.overflowException">
    <id>6602</id>
    <msg>ERROR%3A+Overflow+exception+at+%25%24F.</msg>
  </evtMap>
  <evtMap key="ti.uia.events.UIAErr.indexOutOfRange">
    <id>6636</id>
    <msg>ERROR%3A+Index+out+of+range+at+%25%24F.+%5BINDEX%5D0x%25x</msg>
  </evtMap>
  <evtMap key="ti.uia.events.UIAErr.notImplemented">
    <id>6682</id>
    <msg>ERROR%3A+Attempt+to+access+feature+that+is+not+implemented+at+%25%24F.</msg>
  </evtMap>
  <evtMap key="ti.uia.events.UIAErr.stackOverflow">
    <id>6747</id>
    <msg>ERROR%3A+Stack+Overflow+detected+at+%25%24F.</msg>
  </evtMap>
  <evtMap key="ti.uia.events.UIAErr.illegalInstruction">
    <id>6786</id>
    <msg>ERROR%3A+Illegal+Instruction+executed+at+%25%24F.</msg>
  </evtMap>
  <evtMap key="ti.uia.events.UIAErr.entryPointNotFound">
    <id>6830</id>
    <msg>ERROR%3A+Entry+Point+Not+Found+at+%25%24F.</msg>
  </evtMap>
  <evtMap key="ti.uia.events.UIAErr.moduleNotFound">
    <id>6867</id>
    <msg>ERROR%3A+Module+not+found+at+%25%24F.+%5BMODULE_ID%5D0x%25x.</msg>
  </evtMap>
  <evtMap key="ti.uia.events.UIAErr.floatingPointError">
    <id>6916</id>
    <msg>ERROR%3A+Floating+Point+Error+at+%25%24F.</msg>
  </evtMap>
  <evtMap key="ti.uia.events.UIAErr.invalidParameter">
    <id>6952</id>
    <msg>ERROR%3A+Invalid+Parameter+at+%25%24F.+%5BParamNum%5D%25d+%5BParamValue%5D0x%25x</msg>
  </evtMap>
  <evtMap key="ti.uia.events.UIAEvt.warning">
    <id>7015</id>
    <msg>WARNING%3A+EventCode%3A0x%25x</msg>
  </evtMap>
  <evtMap key="ti.uia.events.UIAEvt.warningWithStr">
    <id>7039</id>
    <msg>WARNING%3A+EventCode%3A0x%25x.+%25%24S</msg>
  </evtMap>
  <evtMap key="ti.uia.events.UIAEvt.info">
    <id>7068</id>
    <msg>INFO%3A+EventCode%3A+0x%25x</msg>
  </evtMap>
  <evtMap key="ti.uia.events.UIAEvt.infoWithStr">
    <id>7090</id>
    <msg>INFO%3A+EventCode%3A0x%25x.++%25%24S</msg>
  </evtMap>
  <evtMap key="ti.uia.events.UIAEvt.detail">
    <id>7117</id>
    <msg>DETAIL%3A+EventCode%3A0x%25x</msg>
  </evtMap>
  <evtMap key="ti.uia.events.UIAEvt.detailWithStr">
    <id>7140</id>
    <msg>DETAIL%3A+EventCode%3A0x%25x.++%25%24S</msg>
  </evtMap>
  <evtMap key="ti.uia.events.UIAEvt.intWithKey">
    <id>7169</id>
    <msg>VALUE%3D%25d+%28AuxData%3D%25d%2C+%25d%29+Key%3A%25%24S</msg>
  </evtMap>
  <evtMap key="ti.uia.events.UIARoundtrip.start">
    <id>7203</id>
    <msg>Roundtrip_Start%3A+%25%24S</msg>
  </evtMap>
  <evtMap key="ti.uia.events.UIARoundtrip.stop">
    <id>7224</id>
    <msg>Roundtrip_Stop%3A+%25%24S</msg>
  </evtMap>
  <evtMap key="ti.uia.events.UIARoundtrip.startInstance">
    <id>7244</id>
    <msg>Roundtrip_StartInstance%3A+%25%24S</msg>
  </evtMap>
  <evtMap key="ti.uia.events.UIARoundtrip.stopInstance">
    <id>7273</id>
    <msg>Roundtrip_StopInstance%3A+%25%24S</msg>
  </evtMap>
  <evtMap key="ti.uia.events.UIARoundtrip.startInstanceWithAdrs">
    <id>7301</id>
    <msg>Roundtrip_StartInstanceWithAdrs%3A+%25%24S</msg>
  </evtMap>
  <evtMap key="ti.uia.events.UIARoundtrip.stopInstanceWithAdrs">
    <id>7338</id>
    <msg>Roundtrip_StopInstanceWithAdrs%3A+%25%24S</msg>
  </evtMap>
  <evtMap key="ti.uia.events.UIARoundtrip.startInstanceWithStr">
    <id>7374</id>
    <msg>Roundtrip_StartInstanceWithStr%3A+%25%24S</msg>
  </evtMap>
  <evtMap key="ti.uia.events.UIARoundtrip.stopInstanceWithStr">
    <id>7410</id>
    <msg>Roundtrip_StopInstanceWithStr%3A+%25%24S</msg>
  </evtMap>
  <evtMap key="ti.uia.events.UIAStatistic.cpuLoad">
    <id>7445</id>
    <msg>CPU+Load%3A+NumCycles%3D%25d</msg>
  </evtMap>
  <evtMap key="ti.uia.events.UIAStatistic.cpuLoadByInstance">
    <id>7468</id>
    <msg>CPU+Load+for+%25s+%28instanceId+%3D+0x%25x%29%3A+NumCycles%3D%25d</msg>
  </evtMap>
  <evtMap key="ti.uia.events.UIAStatistic.bytesProcessed">
    <id>7518</id>
    <msg>Bytes+Processed+by+%25s%3A+NumBytes%3D0x%25x</msg>
  </evtMap>
  <evtMap key="ti.uia.events.UIAStatistic.bytesProcessedByInstance">
    <id>7555</id>
    <msg>Bytes+Processed+at+%25%24F+%28InstanceId+0x%25x%29%3A+Num+Bytes%3D%25d</msg>
  </evtMap>
  <evtMap key="ti.uia.events.UIAStatistic.wordsProcessed">
    <id>7610</id>
    <msg>Words+Processed+by+%25s%3A+NumWords%3D0x%25x</msg>
  </evtMap>
  <evtMap key="ti.uia.events.UIAStatistic.wordsProcessedByInstance">
    <id>7647</id>
    <msg>Words+Processed+at+%25%24F+%28InstanceId+0x%25x%29%3A+Num+Words%3D%25d</msg>
  </evtMap>
  <evtMap key="ti.uia.events.UIAStatistic.freeBytes">
    <id>7702</id>
    <msg>Heap+at+%25%24F+%28HeapId+0x%25x%29%3A+Free+Bytes%3D%25d</msg>
  </evtMap>
  <evtMap key="ti.uia.events.UIASync.syncPoint">
    <id>7743</id>
    <msg>Sync+Point%3A++SerialNumber%3D0x%25x%2C+CpuTStamp+%5BLSW%3D0x%25x%2C+MSW%3D0x%25x%5D%2C+GlobalTStamp+%5BLSW%3D0x%25x%2C+MSW%3D0x%25x%5D%2C+CpuCyclesPerCpuTimerTick%3D%25d%2C+CpuFreq+%5BLSW%3D0x%25x%2C+MSW%3D0x%25x%5D</msg>
  </evtMap>
  <evtMap key="ti.uia.events.UIASync.syncPointAfterHalt">
    <id>7900</id>
    <msg>Sync+Point+After+Halt%3A++SerialNumber%3D0x%25x%2C+CpuTStamp+%5BLSW%3D0x%25x%2C+MSW%3D0x%25x%5D%2C+GlobalTStamp+%5BLSW%3D0x%25x%2C+MSW%3D0x%25x%5D%2C+CpuCyclesPerCpuTimerTick%3D%25d%2C+CpuFreq+%5BLSW%3D0x%25x%2C+MSW%3D0x%25x%5D</msg>
  </evtMap>
  <evtMap key="ti.uia.events.UIASync.globalTimerFreq">
    <id>8068</id>
    <msg>Sync+Point+Global+Timer+Freq%3A++SerialNumber%3D0x%25x%2C+CpuCyclesPerGlobalTimerTick%3D%25d%2C+GlobalTimerFreq+%5BLSW%3D0x%25x%2C+MSW%3D0x%25x%5D</msg>
  </evtMap>
  <evtMap key="ti.uia.events.UIASync.syncPointUserProvidedData">
    <id>8187</id>
    <msg>Sync+Point+User+Data%3A+SerialNumber%3D0x%25x%2C+%25%24S</msg>
  </evtMap>
  <evtMap key="ti.sysbios.utils.Load.LS_cpuLoad">
    <id>8232</id>
    <msg>LS_cpuLoad%3A+%25d%25%25</msg>
  </evtMap>
  <evtMap key="ti.sysbios.utils.Load.LS_hwiLoad">
    <id>8249</id>
    <msg>LS_hwiLoad%3A+%25d%2C%25d</msg>
  </evtMap>
  <evtMap key="ti.sysbios.utils.Load.LS_swiLoad">
    <id>8267</id>
    <msg>LS_swiLoad%3A+%25d%2C%25d</msg>
  </evtMap>
  <evtMap key="ti.sysbios.utils.Load.LS_taskLoad">
    <id>8285</id>
    <msg>LS_taskLoad%3A+0x%25x%2C%25d%2C%25d%2C0x%25x</msg>
  </evtMap>
</xdc.runtime.Types.RtaDecoderData>
